q_analysis-0.1.2.dist-info/METADATA
q_analysis-0.1.2.dist-info/WHEEL
q_analysis/__init__.py
q_analysis/datasets.py
q_analysis/examples/__init__.py
q_analysis/examples/scale_free_configurational.py
q_analysis/q_analysis.cpython-39-i386-linux-gnu.so
q_analysis/simplicial_complex.py
q_analysis/stat.py
q_analysis/transformers.py
q_analysis/viz.py
q_analysis-0.1.2.dist-info/RECORD
