Metadata-Version: 2.4
Name: q-analysis
Version: 0.1.2
Classifier: Programming Language :: Python :: 3
Classifier: Programming Language :: Rust
Classifier: License :: OSI Approved :: GNU General Public License v3 (GPLv3)
Classifier: Operating System :: OS Independent
Requires-Dist: numpy
Requires-Dist: scipy
Requires-Dist: networkx
Requires-Dist: scikit-learn
Requires-Dist: pandas
Requires-Dist: matplotlib
Requires-Dist: seaborn
Requires-Dist: statannotations
Requires-Dist: gdown
Summary: A package for Q-analysis of complex networks
Author: Nikita Smirnov
License: GNU General Public License v3.0
Requires-Python: >=3.8, <=3.10.17
Project-URL: Homepage, https://github.com/pakrentos/q-analysis
